{
  "0": {
    "basicblocks": 259,
    "calls": "6",
    "file": "DelayAndSum.cpp",
    "fileloc": 5,
    "instructions": 471,
    "loads": {
      "L": 16,
      "T": 6
    },
    "name": "DelayAndSum",
    "total_instructions": 47832
  },
  "1": {
    "basicblocks": 954,
    "calls": "",
    "file": "hls_cordic_apfixed.h",
    "fileloc": 51,
    "instructions": 1834,
    "loads": {
      "L": 3
    },
    "name": "cordic_circ_apfixed<10, 3, 0>",
    "stores": {
      "L": 3
    },
    "total_instructions": 1834
  },
  "2": {
    "basicblocks": 1714,
    "calls": "",
    "file": "hls_cordic_apfixed.h",
    "fileloc": 51,
    "instructions": 3306,
    "loads": {
      "L": 3
    },
    "name": "cordic_circ_apfixed<18, 3, 0>",
    "stores": {
      "L": 3
    },
    "total_instructions": 3306
  },
  "3": {
    "basicblocks": 53,
    "calls": "",
    "file": "CalculateWeights.cpp",
    "fileloc": 4,
    "instructions": 103,
    "loads": {
      "L": 4
    },
    "name": "CalculateElement",
    "stores": {
      "L": 2
    },
    "total_instructions": 11839
  },
  "4": {
    "basicblocks": 39,
    "calls": "",
    "file": "hls_cordic_apfixed.h",
    "fileloc": 32,
    "instructions": 74,
    "name": "circ_range_redux<8, 4, 9>",
    "stores": {
      "L": 2
    },
    "total_instructions": 74
  },
  "5": {
    "basicblocks": 111,
    "calls": "7 2",
    "file": "hls_cordic_apfixed.h",
    "fileloc": 201,
    "instructions": 284,
    "loads": {
      "L": 38
    },
    "name": "generic_sincos<16, 1>",
    "stores": {
      "L": 13
    },
    "total_instructions": 3662
  },
  "6": {
    "basicblocks": 1,
    "calls": "3 3 3 3",
    "file": "CalculateWeights.cpp",
    "fileloc": 17,
    "instructions": 5,
    "name": "CalculateWeights",
    "total_instructions": 47361
  },
  "7": {
    "basicblocks": 39,
    "calls": "",
    "file": "hls_cordic_apfixed.h",
    "fileloc": 32,
    "instructions": 72,
    "name": "circ_range_redux<16, 1, 17>",
    "stores": {
      "L": 2
    },
    "total_instructions": 72
  },
  "8": {
    "basicblocks": 111,
    "calls": "4 1",
    "file": "hls_cordic_apfixed.h",
    "fileloc": 201,
    "instructions": 292,
    "loads": {
      "L": 38
    },
    "name": "generic_sincos<8, 4>",
    "stores": {
      "L": 13
    },
    "total_instructions": 2200
  }
}